scrubadub_address/__init__.py
scrubadub_address/detectors/__init__.py
scrubadub_address/detectors/address.py
scrubadub_address-2.0.1.dist-info/LICENSE
scrubadub_address-2.0.1.dist-info/METADATA
scrubadub_address-2.0.1.dist-info/WHEEL
scrubadub_address-2.0.1.dist-info/entry_points.txt
scrubadub_address-2.0.1.dist-info/top_level.txt
scrubadub_address-2.0.1.dist-info/RECORD
