Metadata-Version: 2.1
Name: scrubadub-address
Version: 2.0.1
Summary: Use the Stanford NER model to clean personally identifiable information from dirty dirty text.
Home-page: https://github.com/LeapBeyond/scrubadub_address
Author: Thomas Bird
Author-email: thomas.bird@leapbeyond.ai
License: MIT
Download-URL: https://github.com/LeapBeyond/scrubadub_address/archives/master
Platform: UNKNOWN
Classifier: Intended Audience :: Developers
Classifier: Development Status :: 5 - Production/Stable
Classifier: License :: OSI Approved :: Apache Software License
Classifier: Natural Language :: English
Classifier: Programming Language :: Python
Classifier: Programming Language :: Python :: 3
Classifier: Programming Language :: Python :: 3.5
Classifier: Programming Language :: Python :: 3.6
Classifier: Programming Language :: Python :: 3.7
Classifier: Programming Language :: Python :: 3.8
Classifier: Topic :: Software Development :: Libraries
Classifier: Topic :: Scientific/Engineering :: Information Analysis
Classifier: Topic :: Text Processing
Classifier: Topic :: Utilities
License-File: LICENSE
Requires-Dist: pyap
Requires-Dist: scrubadub (>=2.0.0rc0)
